norve/__init__.py
norve/__main__.py
norve/grammar.lark
norve/parser.py
norve/repl.py
norve/run_pipe.py
norve/token_utils.py
norve/api/__init__.py
norve/api/core.py
norve/api/dataframe_capture.py
norve/api/result_types.py
norve/api/utils.py
norve/ast/__init__.py
norve/ast/agg.py
norve/ast/expr.py
norve/ast/pipeline.py
norve/ast/steps.py
norve/error/block_split.py
norve/error/error_utils.py
norve/error/exceptions.py
norve/error/syntax.py
norve/interpreter/__init__.py
norve/interpreter/ast_utils.py
norve/interpreter/expr_eval.py
norve/interpreter/pipeline.py
norve/interpreter/safe_funcs.py
norve/interpreter/utils.py
norve/interpreter/backend/__init__.py
norve/interpreter/backend/column_utils.py
norve/interpreter/backend/core.py
norve/interpreter/backend/display.py
norve/interpreter/backend/grouping.py
norve/interpreter/backend/joins.py
norve/transformer/__init__.py
norve/transformer/core.py
norve/transformer/expressions.py
norve/transformer/pipelines.py
norve/transformer/statements.py
norve/transformer/utils.py
norve-0.2.2.dist-info/licenses/LICENSE
norve-0.2.2.dist-info/METADATA
norve-0.2.2.dist-info/WHEEL
norve-0.2.2.dist-info/entry_points.txt
norve-0.2.2.dist-info/top_level.txt
norve-0.2.2.dist-info/RECORD
