Metadata-Version: 2.4
Name: norve
Version: 0.2.2
Summary: Multi-Source Data Processing Language
Author: LoXewyX
License: MIT
Project-URL: Homepage, https://github.com/LoXewyX/Norvelang
Project-URL: Bug Reports, https://github.com/LoXewyX/Norvelang/issues
Project-URL: Source, https://github.com/LoXewyX/Norvelang
Project-URL: Documentation, https://github.com/LoXewyX/Norvelang/blob/main/README.md
Keywords: query-language,data-processing,dsl,pandas,csv,xlsx,excel,sqlite,json,xml,interpreter,python-api,data-analysis,sql-like,mathematical-expressions,joins,aggregations,domain-specific-language
Classifier: Intended Audience :: Developers
Classifier: Intended Audience :: Science/Research
Classifier: Topic :: Software Development :: Interpreters
Classifier: Topic :: Database
Classifier: Topic :: Scientific/Engineering :: Information Analysis
Classifier: License :: OSI Approved :: MIT License
Classifier: Programming Language :: Python :: 3
Classifier: Programming Language :: Python :: 3.8
Classifier: Programming Language :: Python :: 3.9
Classifier: Programming Language :: Python :: 3.10
Classifier: Programming Language :: Python :: 3.11
Classifier: Programming Language :: Python :: 3.12
Classifier: Programming Language :: Python :: 3.13
Classifier: Operating System :: OS Independent
Requires-Python: >=3.8
License-File: LICENSE
Requires-Dist: lark
Requires-Dist: lark-cython
Requires-Dist: pandas
Requires-Dist: openpyxl
Provides-Extra: dev
Requires-Dist: pytest; extra == "dev"
Requires-Dist: pylint; extra == "dev"
Requires-Dist: twine; extra == "dev"
Requires-Dist: build; extra == "dev"
Provides-Extra: test
Requires-Dist: pytest; extra == "test"
Dynamic: license-file
